.flake8
.gitignore
.isort.cfg
.markdownlint.json
.pre-commit-config.yaml
.pylintrc
LICENSE
README.md
question.stack.md
setup.cfg
setup.py
.github/workflows/ci.yaml
.github/workflows/release.yaml
code_golf_bagnon_sort/__init__.py
code_golf_bagnon_sort/bag.py
code_golf_bagnon_sort/checker.py
code_golf_bagnon_sort/item.py
code_golf_bagnon_sort.egg-info/PKG-INFO
code_golf_bagnon_sort.egg-info/SOURCES.txt
code_golf_bagnon_sort.egg-info/dependency_links.txt
code_golf_bagnon_sort.egg-info/requires.txt
code_golf_bagnon_sort.egg-info/top_level.txt
tests/__init__.py
tests/conftest.py
tests/test_bag.py
tests/test_integration.py