Metadata-Version: 2.1
Name: code-golf-bagnon-sort
Version: 0.0.1
Home-page: https://github.com/Pierre-Sassoulas/code-golf-bagnon-sort
Author: Pierre Sassoulas
Author-email: pierre.sassoulas@gmail.com
Classifier: Intended Audience :: Developers
Classifier: Operating System :: OS Independent
Classifier: Programming Language :: Python :: 3.7
Classifier: Programming Language :: Python :: 3.8
Classifier: Programming Language :: Python :: 3.9
Classifier: Programming Language :: Python :: 3.10
Requires-Python: >=3.7
Provides-Extra: test
License-File: LICENSE
